Workbook
Name aporte: APP!$D$19
Name dividendos: APP!$D$23
Name patrimonio: APP!$D$22
Name perfil: APP!$G$14
Name qnd_anos: APP!$D$20
Name RENDIMENTO: APP!$D$15
Name rendimento_carteira: APP!$D$15
Name SALARIO: APP!$D$14
Name taxa_mensal: APP!$D$21

Sheet APP
B13: DADOS PARA INVESTIMENTOS | F13: INFORMAÇOES COMPLEMENTARES
B14: SALARIO | D14: 3000 | F14: Qual seu perfil de investidor ? | G14: CONSERVADOR
B15: RENDIMENTO DE CARTEIRA | D15: 0.01 | F15: Valor investido por mês | G15: =aporte -> 300
B16: SUGESTÃO DE INVESTIMENTO (30%) | D16: =SALARIO*30% -> 900
B18: INVESTIMENTO MENSAL DESEJADO | F18: RECOMENDAÇAO DE DISTRIBUIÇAO DE INVESTIMENTO
B19: Quanto deseja investir por mês? | D19: 300 | F19: TIPO DE FII | G19: Percentual Sugerido | H19: Valores
B20: Por quantos anos? | D20: 5 | F20: PAPEL | G20: =VLOOKUP(perfil&"-"&F20,DADOS!A:D,4,) -> 0.3 | H20: =$G$15*G20 -> 90
B21: Qual a taxa de rendimento mensal? | D21: 0.0138 | F21: TIJOLO | G21: =VLOOKUP(perfil&"-"&F21,DADOS!A:D,4,) -> 0.5 | H21: =$G$15*G21 -> 150
B22: Patrimônio acumulado final | D22: =FV(taxa_mensal,qnd_anos*12,aporte*-1) -> 27735.138 | F22: HÍBRIDOS | G22: =VLOOKUP(perfil&"-"&F22,DADOS!A:D,4,) -> 0.1 | H22: =$G$15*G22 -> 30
B23: Dividendos mensais | D23: =patrimonio*rendimento_carteira -> 277.35138 | F23: FOFs | G23: =VLOOKUP(perfil&"-"&F23,DADOS!A:D,4,) -> 0.1 | H23: =$G$15*G23 -> 30
F24: DESENVOLVIMENTO | G24: =VLOOKUP(perfil&"-"&F24,DADOS!A:D,4,) -> 0 | H24: =$G$15*G24 -> 0
B25: CENARIOS FUTUROS | D25: DIVIDENDOS | F25: HOTELARIAS | G25: =VLOOKUP(perfil&"-"&F25,DADOS!A:D,4,) -> 0 | H25: =$G$15*G25 -> 0
A26: 2 | B26: Quanto em 2 Anos? | C26: =FV(taxa_mensal,A26*12,aporte*-1) -> 8467.1363 | D26: =C26*RENDIMENTO -> 84.671363
A27: 5 | B27: Quanto em 5 Anos? | C27: =FV(taxa_mensal,A27*12,aporte*-1) -> 27735.138 | D27: =C27*RENDIMENTO -> 277.35138
A28: 10 | B28: Quanto em 10 Anos? | C28: =FV(taxa_mensal,A28*12,aporte*-1) -> 90855.219 | D28: =C28*RENDIMENTO -> 908.55219
A29: 20 | B29: Quanto em 20 Anos? | C29: =FV(taxa_mensal,A29*12,aporte*-1) -> 561425.29 | D29: =C29*RENDIMENTO -> 5614.2529
A30: 30 | B30: Quanto em 30 Anos? | C30: =FV(taxa_mensal,A30*12,aporte*-1) -> 2998667.7 | D30: =C30*RENDIMENTO -> 29986.677

Sheet DADOS
A1: CHAVE | B1: PERFIL | C1: TIPO DE FII | D1: %
A2: =B2&"-"&C2 -> Conservador-PAPEL | B2: Conservador | C2: PAPEL | D2: 0.3
A3: =B3&"-"&C3 -> Conservador-TIJOLO | B3: Conservador | C3: TIJOLO | D3: 0.5
A4: =B4&"-"&C4 -> Conservador-HÍBRIDOS | B4: Conservador | C4: HÍBRIDOS | D4: 0.1
A5: =B5&"-"&C5 -> Conservador-FOFs | B5: Conservador | C5: FOFs | D5: 0.1
A6: =B6&"-"&C6 -> Conservador-DESENVOLVIMENTO | B6: Conservador | C6: DESENVOLVIMENTO | D6: 0
A7: =B7&"-"&C7 -> Conservador-HOTELARIAS | B7: Conservador | C7: HOTELARIAS | D7: 0
A8: =B8&"-"&C8 -> Moderado-PAPEL | B8: Moderado | C8: PAPEL | D8: 0.32
A9: =B9&"-"&C9 -> Moderado-TIJOLO | B9: Moderado | C9: TIJOLO | D9: 0.35
A10: =B10&"-"&C10 -> Moderado-HÍBRIDOS | B10: Moderado | C10: HÍBRIDOS | D10: 0.08
A11: =B11&"-"&C11 -> Moderado-FOFs | B11: Moderado | C11: FOFs | D11: 0.05
A12: =B12&"-"&C12 -> Moderado-DESENVOLVIMENTO | B12: Moderado | C12: DESENVOLVIMENTO | D12: 0.1
A13: =B13&"-"&C13 -> Moderado-HOTELARIAS | B13: Moderado | C13: HOTELARIAS | D13: 0.1
... A19: =B19&"-"&C19 -> Agressivo-HOTELARIAS | B19: Agressivo | C19: HOTELARIAS | D19: 0.1
